alma/__init__.py
alma/__main__.py
alma/defaultParamsPyALMA3.toml
PyALMA3-1.0.1.dist-info/LICENSE
PyALMA3-1.0.1.dist-info/METADATA
PyALMA3-1.0.1.dist-info/WHEEL
PyALMA3-1.0.1.dist-info/top_level.txt
PyALMA3-1.0.1.dist-info/RECORD
