Metadata-Version: 2.1
Name: PyALMA3
Version: 1.0.1
Summary: Python plAnetary Love nuMbers cALculator
Home-page: https://github.com/drsaikirant88/PyALMA3
Author: Marshall J. Styczinski, Saikiran Tharimena, Daniele Melini, Giorgio Spada, Steven D. Vance, Flavio Petricca, Amirhossein Bagheri
Author-email: itsmoosh@gmail.com
Project-URL: Bug tracker, https://github.com/drsaikirant88/PyALMA3/issues
Project-URL: Publication, https://doi.org/10.1093/gji/ggac263
Classifier: Programming Language :: Python :: 3.8
Classifier: License :: OSI Approved :: GNU General Public License v3 (GPLv3)
Classifier: Operating System :: OS Independent
License-File: LICENSE
Requires-Dist: numpy >=1.26.3
Requires-Dist: mpmath >=1.3.0
Requires-Dist: psutil >=5.9.7
Requires-Dist: joblib >=1.3.2
Requires-Dist: toml >=0.10.2
